{"nodes": [{"id": "index", "label": "index.ts", "file_type": "code", "source_file": "src\\main\\index.ts", "source_location": "L1"}, {"id": "index_getprojectspath", "label": "getProjectsPath()", "file_type": "code", "source_file": "src\\main\\index.ts", "source_location": "L48"}, {"id": "index_loadconfig", "label": "loadConfig()", "file_type": "code", "source_file": "src\\main\\index.ts", "source_location": "L53"}, {"id": "index_saveconfig", "label": "saveConfig()", "file_type": "code", "source_file": "src\\main\\index.ts", "source_location": "L94"}, {"id": "index_findworkspace", "label": "findWorkspace()", "file_type": "code", "source_file": "src\\main\\index.ts", "source_location": "L101"}, {"id": "index_ensurepath", "label": "ensurePath()", "file_type": "code", "source_file": "src\\main\\index.ts", "source_location": "L115"}, {"id": "index_createptysession", "label": "createPtySession()", "file_type": "code", "source_file": "src\\main\\index.ts", "source_location": "L158"}, {"id": "index_createwindow", "label": "createWindow()", "file_type": "code", "source_file": "src\\main\\index.ts", "source_location": "L196"}], "edges": [{"source": "index", "target": "electron", "relation": "imports_from", "confidence": "EXTRACTED", "source_file": "src\\main\\index.ts", "source_location": "L1", "weight": 1.0}, {"source": "index", "target": "path", "relation": "imports_from", "confidence": "EXTRACTED", "source_file": "src\\main\\index.ts", "source_location": "L2", "weight": 1.0}, {"source": "index", "target": "fs", "relation": "imports_from", "confidence": "EXTRACTED", "source_file": "src\\main\\index.ts", "source_location": "L3", "weight": 1.0}, {"source": "index", "target": "child_process", "relation": "imports_from", "confidence": "EXTRACTED", "source_file": "src\\main\\index.ts", "source_location": "L4", "weight": 1.0}, {"source": "index", "target": "node_pty", "relation": "imports_from", "confidence": "EXTRACTED", "source_file": "src\\main\\index.ts", "source_location": "L5", "weight": 1.0}, {"source": "index", "target": "icon_png_asset", "relation": "imports_from", "confidence": "EXTRACTED", "source_file": "src\\main\\index.ts", "source_location": "L6", "weight": 1.0}, {"source": "index", "target": "sqlite_task_service", "relation": "imports_from", "confidence": "EXTRACTED", "source_file": "src\\main\\index.ts", "source_location": "L7", "weight": 1.0}, {"source": "index", "target": "paths", "relation": "imports_from", "confidence": "EXTRACTED", "source_file": "src\\main\\index.ts", "source_location": "L8", "weight": 1.0}, {"source": "index", "target": "vault_importer", "relation": "imports_from", "confidence": "EXTRACTED", "source_file": "src\\main\\index.ts", "source_location": "L9", "weight": 1.0}, {"source": "index", "target": "vault_service", "relation": "imports_from", "confidence": "EXTRACTED", "source_file": "src\\main\\index.ts", "source_location": "L10", "weight": 1.0}, {"source": "index", "target": "backup_service", "relation": "imports_from", "confidence": "EXTRACTED", "source_file": "src\\main\\index.ts", "source_location": "L11", "weight": 1.0}, {"source": "index", "target": "mcp_register", "relation": "imports_from", "confidence": "EXTRACTED", "source_file": "src\\main\\index.ts", "source_location": "L18", "weight": 1.0}, {"source": "index", "target": "index_getprojectspath", "relation": "contains", "confidence": "EXTRACTED", "source_file": "src\\main\\index.ts", "source_location": "L48", "weight": 1.0}, {"source": "index", "target": "index_loadconfig", "relation": "contains", "confidence": "EXTRACTED", "source_file": "src\\main\\index.ts", "source_location": "L53", "weight": 1.0}, {"source": "index", "target": "index_saveconfig", "relation": "contains", "confidence": "EXTRACTED", "source_file": "src\\main\\index.ts", "source_location": "L94", "weight": 1.0}, {"source": "index", "target": "index_findworkspace", "relation": "contains", "confidence": "EXTRACTED", "source_file": "src\\main\\index.ts", "source_location": "L101", "weight": 1.0}, {"source": "index", "target": "index_ensurepath", "relation": "contains", "confidence": "EXTRACTED", "source_file": "src\\main\\index.ts", "source_location": "L115", "weight": 1.0}, {"source": "index", "target": "index_createptysession", "relation": "contains", "confidence": "EXTRACTED", "source_file": "src\\main\\index.ts", "source_location": "L158", "weight": 1.0}, {"source": "index", "target": "index_createwindow", "relation": "contains", "confidence": "EXTRACTED", "source_file": "src\\main\\index.ts", "source_location": "L196", "weight": 1.0}, {"source": "index_loadconfig", "target": "index_getprojectspath", "relation": "calls", "confidence": "EXTRACTED", "source_file": "src\\main\\index.ts", "source_location": "L54", "weight": 1.0}, {"source": "index_saveconfig", "target": "index_getprojectspath", "relation": "calls", "confidence": "EXTRACTED", "source_file": "src\\main\\index.ts", "source_location": "L95", "weight": 1.0}, {"source": "index_createptysession", "target": "index_findworkspace", "relation": "calls", "confidence": "EXTRACTED", "source_file": "src\\main\\index.ts", "source_location": "L170", "weight": 1.0}]}