{"nodes": [{"id": "graph_config", "label": "graph-config.ts", "file_type": "code", "source_file": "src\\graph\\graph-config.ts", "source_location": "L1"}, {"id": "graph_config_registergraphprovider", "label": "registerGraphProvider()", "file_type": "code", "source_file": "src\\graph\\graph-config.ts", "source_location": "L26"}, {"id": "graph_config_creategraphservice", "label": "createGraphService()", "file_type": "code", "source_file": "src\\graph\\graph-config.ts", "source_location": "L30"}], "edges": [{"source": "graph_config", "target": "graph_service_interface", "relation": "imports_from", "confidence": "EXTRACTED", "source_file": "src\\graph\\graph-config.ts", "source_location": "L1", "weight": 1.0}, {"source": "graph_config", "target": "graph_config_registergraphprovider", "relation": "contains", "confidence": "EXTRACTED", "source_file": "src\\graph\\graph-config.ts", "source_location": "L26", "weight": 1.0}, {"source": "graph_config", "target": "graph_config_creategraphservice", "relation": "contains", "confidence": "EXTRACTED", "source_file": "src\\graph\\graph-config.ts", "source_location": "L30", "weight": 1.0}]}