{"nodes": [{"id": "project_context_builder", "label": "project-context-builder.ts", "file_type": "code", "source_file": "src\\tasks\\mcp-tools\\project-context-builder.ts", "source_location": "L1"}, {"id": "project_context_builder_buildprojectcontext", "label": "buildProjectContext()", "file_type": "code", "source_file": "src\\tasks\\mcp-tools\\project-context-builder.ts", "source_location": "L49"}, {"id": "project_context_builder_fetchproject", "label": "fetchProject()", "file_type": "code", "source_file": "src\\tasks\\mcp-tools\\project-context-builder.ts", "source_location": "L79"}, {"id": "project_context_builder_pickactivephase", "label": "pickActivePhase()", "file_type": "code", "source_file": "src\\tasks\\mcp-tools\\project-context-builder.ts", "source_location": "L86"}, {"id": "project_context_builder_pickactivetasks", "label": "pickActiveTasks()", "file_type": "code", "source_file": "src\\tasks\\mcp-tools\\project-context-builder.ts", "source_location": "L99"}, {"id": "project_context_builder_picklastsession", "label": "pickLastSession()", "file_type": "code", "source_file": "src\\tasks\\mcp-tools\\project-context-builder.ts", "source_location": "L110"}, {"id": "project_context_builder_pickopenconversations", "label": "pickOpenConversations()", "file_type": "code", "source_file": "src\\tasks\\mcp-tools\\project-context-builder.ts", "source_location": "L120"}, {"id": "project_context_builder_loadfilesource", "label": "loadFileSource()", "file_type": "code", "source_file": "src\\tasks\\mcp-tools\\project-context-builder.ts", "source_location": "L146"}, {"id": "project_context_builder_loadconventions", "label": "loadConventions()", "file_type": "code", "source_file": "src\\tasks\\mcp-tools\\project-context-builder.ts", "source_location": "L160"}, {"id": "project_context_builder_loadrecentdecisions", "label": "loadRecentDecisions()", "file_type": "code", "source_file": "src\\tasks\\mcp-tools\\project-context-builder.ts", "source_location": "L176"}, {"id": "project_context_builder_readmarkdown", "label": "readMarkdown()", "file_type": "code", "source_file": "src\\tasks\\mcp-tools\\project-context-builder.ts", "source_location": "L190"}, {"id": "project_context_builder_stripfrontmatter", "label": "stripFrontmatter()", "file_type": "code", "source_file": "src\\tasks\\mcp-tools\\project-context-builder.ts", "source_location": "L206"}, {"id": "project_context_builder_summarize", "label": "summarize()", "file_type": "code", "source_file": "src\\tasks\\mcp-tools\\project-context-builder.ts", "source_location": "L213"}], "edges": [{"source": "project_context_builder", "target": "fs", "relation": "imports_from", "confidence": "EXTRACTED", "source_file": "src\\tasks\\mcp-tools\\project-context-builder.ts", "source_location": "L1", "weight": 1.0}, {"source": "project_context_builder", "target": "path", "relation": "imports_from", "confidence": "EXTRACTED", "source_file": "src\\tasks\\mcp-tools\\project-context-builder.ts", "source_location": "L2", "weight": 1.0}, {"source": "project_context_builder", "target": "task_types", "relation": "imports_from", "confidence": "EXTRACTED", "source_file": "src\\tasks\\mcp-tools\\project-context-builder.ts", "source_location": "L3", "weight": 1.0}, {"source": "project_context_builder", "target": "project_repository_interface", "relation": "imports_from", "confidence": "EXTRACTED", "source_file": "src\\tasks\\mcp-tools\\project-context-builder.ts", "source_location": "L11", "weight": 1.0}, {"source": "project_context_builder", "target": "context_source_repository_interface", "relation": "imports_from", "confidence": "EXTRACTED", "source_file": "src\\tasks\\mcp-tools\\project-context-builder.ts", "source_location": "L12", "weight": 1.0}, {"source": "project_context_builder", "target": "phase_repository_interface", "relation": "imports_from", "confidence": "EXTRACTED", "source_file": "src\\tasks\\mcp-tools\\project-context-builder.ts", "source_location": "L13", "weight": 1.0}, {"source": "project_context_builder", "target": "task_repository_interface", "relation": "imports_from", "confidence": "EXTRACTED", "source_file": "src\\tasks\\mcp-tools\\project-context-builder.ts", "source_location": "L14", "weight": 1.0}, {"source": "project_context_builder", "target": "session_repository_interface", "relation": "imports_from", "confidence": "EXTRACTED", "source_file": "src\\tasks\\mcp-tools\\project-context-builder.ts", "source_location": "L15", "weight": 1.0}, {"source": "project_context_builder", "target": "conversation_repository_interface", "relation": "imports_from", "confidence": "EXTRACTED", "source_file": "src\\tasks\\mcp-tools\\project-context-builder.ts", "source_location": "L16", "weight": 1.0}, {"source": "project_context_builder", "target": "project_context_builder_buildprojectcontext", "relation": "contains", "confidence": "EXTRACTED", "source_file": "src\\tasks\\mcp-tools\\project-context-builder.ts", "source_location": "L49", "weight": 1.0}, {"source": "project_context_builder", "target": "project_context_builder_fetchproject", "relation": "contains", "confidence": "EXTRACTED", "source_file": "src\\tasks\\mcp-tools\\project-context-builder.ts", "source_location": "L79", "weight": 1.0}, {"source": "project_context_builder", "target": "project_context_builder_pickactivephase", "relation": "contains", "confidence": "EXTRACTED", "source_file": "src\\tasks\\mcp-tools\\project-context-builder.ts", "source_location": "L86", "weight": 1.0}, {"source": "project_context_builder", "target": "project_context_builder_pickactivetasks", "relation": "contains", "confidence": "EXTRACTED", "source_file": "src\\tasks\\mcp-tools\\project-context-builder.ts", "source_location": "L99", "weight": 1.0}, {"source": "project_context_builder", "target": "project_context_builder_picklastsession", "relation": "contains", "confidence": "EXTRACTED", "source_file": "src\\tasks\\mcp-tools\\project-context-builder.ts", "source_location": "L110", "weight": 1.0}, {"source": "project_context_builder", "target": "project_context_builder_pickopenconversations", "relation": "contains", "confidence": "EXTRACTED", "source_file": "src\\tasks\\mcp-tools\\project-context-builder.ts", "source_location": "L120", "weight": 1.0}, {"source": "project_context_builder", "target": "project_context_builder_loadfilesource", "relation": "contains", "confidence": "EXTRACTED", "source_file": "src\\tasks\\mcp-tools\\project-context-builder.ts", "source_location": "L146", "weight": 1.0}, {"source": "project_context_builder", "target": "project_context_builder_loadconventions", "relation": "contains", "confidence": "EXTRACTED", "source_file": "src\\tasks\\mcp-tools\\project-context-builder.ts", "source_location": "L160", "weight": 1.0}, {"source": "project_context_builder", "target": "project_context_builder_loadrecentdecisions", "relation": "contains", "confidence": "EXTRACTED", "source_file": "src\\tasks\\mcp-tools\\project-context-builder.ts", "source_location": "L176", "weight": 1.0}, {"source": "project_context_builder", "target": "project_context_builder_readmarkdown", "relation": "contains", "confidence": "EXTRACTED", "source_file": "src\\tasks\\mcp-tools\\project-context-builder.ts", "source_location": "L190", "weight": 1.0}, {"source": "project_context_builder", "target": "project_context_builder_stripfrontmatter", "relation": "contains", "confidence": "EXTRACTED", "source_file": "src\\tasks\\mcp-tools\\project-context-builder.ts", "source_location": "L206", "weight": 1.0}, {"source": "project_context_builder", "target": "project_context_builder_summarize", "relation": "contains", "confidence": "EXTRACTED", "source_file": "src\\tasks\\mcp-tools\\project-context-builder.ts", "source_location": "L213", "weight": 1.0}, {"source": "project_context_builder_buildprojectcontext", "target": "project_context_builder_fetchproject", "relation": "calls", "confidence": "EXTRACTED", "source_file": "src\\tasks\\mcp-tools\\project-context-builder.ts", "source_location": "L55", "weight": 1.0}, {"source": "project_context_builder_buildprojectcontext", "target": "project_context_builder_pickactivephase", "relation": "calls", "confidence": "EXTRACTED", "source_file": "src\\tasks\\mcp-tools\\project-context-builder.ts", "source_location": "L63", "weight": 1.0}, {"source": "project_context_builder_buildprojectcontext", "target": "project_context_builder_pickactivetasks", "relation": "calls", "confidence": "EXTRACTED", "source_file": "src\\tasks\\mcp-tools\\project-context-builder.ts", "source_location": "L64", "weight": 1.0}, {"source": "project_context_builder_buildprojectcontext", "target": "project_context_builder_picklastsession", "relation": "calls", "confidence": "EXTRACTED", "source_file": "src\\tasks\\mcp-tools\\project-context-builder.ts", "source_location": "L65", "weight": 1.0}, {"source": "project_context_builder_buildprojectcontext", "target": "project_context_builder_pickopenconversations", "relation": "calls", "confidence": "EXTRACTED", "source_file": "src\\tasks\\mcp-tools\\project-context-builder.ts", "source_location": "L66", "weight": 1.0}, {"source": "project_context_builder_buildprojectcontext", "target": "project_context_builder_loadfilesource", "relation": "calls", "confidence": "EXTRACTED", "source_file": "src\\tasks\\mcp-tools\\project-context-builder.ts", "source_location": "L68", "weight": 1.0}, {"source": "project_context_builder_buildprojectcontext", "target": "project_context_builder_loadconventions", "relation": "calls", "confidence": "EXTRACTED", "source_file": "src\\tasks\\mcp-tools\\project-context-builder.ts", "source_location": "L69", "weight": 1.0}, {"source": "project_context_builder_buildprojectcontext", "target": "project_context_builder_loadrecentdecisions", "relation": "calls", "confidence": "EXTRACTED", "source_file": "src\\tasks\\mcp-tools\\project-context-builder.ts", "source_location": "L70", "weight": 1.0}, {"source": "project_context_builder_loadfilesource", "target": "project_context_builder_readmarkdown", "relation": "calls", "confidence": "EXTRACTED", "source_file": "src\\tasks\\mcp-tools\\project-context-builder.ts", "source_location": "L157", "weight": 1.0}, {"source": "project_context_builder_readmarkdown", "target": "project_context_builder_stripfrontmatter", "relation": "calls", "confidence": "EXTRACTED", "source_file": "src\\tasks\\mcp-tools\\project-context-builder.ts", "source_location": "L199", "weight": 1.0}, {"source": "project_context_builder_readmarkdown", "target": "project_context_builder_summarize", "relation": "calls", "confidence": "EXTRACTED", "source_file": "src\\tasks\\mcp-tools\\project-context-builder.ts", "source_location": "L200", "weight": 1.0}]}