{"nodes": [{"id": "sidebar", "label": "Sidebar.tsx", "file_type": "code", "source_file": "src\\renderer\\src\\Sidebar.tsx", "source_location": "L1"}, {"id": "sidebar_toggleproject", "label": "toggleProject()", "file_type": "code", "source_file": "src\\renderer\\src\\Sidebar.tsx", "source_location": "L47"}, {"id": "sidebar_activeprojectid", "label": "activeProjectId()", "file_type": "code", "source_file": "src\\renderer\\src\\Sidebar.tsx", "source_location": "L56"}, {"id": "sidebar_handleformsubmit", "label": "handleFormSubmit()", "file_type": "code", "source_file": "src\\renderer\\src\\Sidebar.tsx", "source_location": "L63"}], "edges": [{"source": "sidebar", "target": "react", "relation": "imports_from", "confidence": "EXTRACTED", "source_file": "src\\renderer\\src\\Sidebar.tsx", "source_location": "L1", "weight": 1.0}, {"source": "sidebar", "target": "index", "relation": "imports_from", "confidence": "EXTRACTED", "source_file": "src\\renderer\\src\\Sidebar.tsx", "source_location": "L2", "weight": 1.0}, {"source": "sidebar", "target": "projectform", "relation": "imports_from", "confidence": "EXTRACTED", "source_file": "src\\renderer\\src\\Sidebar.tsx", "source_location": "L3", "weight": 1.0}, {"source": "sidebar", "target": "settingsmodal", "relation": "imports_from", "confidence": "EXTRACTED", "source_file": "src\\renderer\\src\\Sidebar.tsx", "source_location": "L4", "weight": 1.0}, {"source": "sidebar", "target": "sidebar_toggleproject", "relation": "contains", "confidence": "EXTRACTED", "source_file": "src\\renderer\\src\\Sidebar.tsx", "source_location": "L47", "weight": 1.0}, {"source": "sidebar", "target": "sidebar_activeprojectid", "relation": "contains", "confidence": "EXTRACTED", "source_file": "src\\renderer\\src\\Sidebar.tsx", "source_location": "L56", "weight": 1.0}, {"source": "sidebar", "target": "sidebar_handleformsubmit", "relation": "contains", "confidence": "EXTRACTED", "source_file": "src\\renderer\\src\\Sidebar.tsx", "source_location": "L63", "weight": 1.0}]}